pippy_ls/__init__.py
pippy_ls/__main__.py
pippy_ls/colors.py
pippy_ls/config.toml
pippy_ls/custom_errors.py
pippy_ls/defaults.py
pippy_ls/feed.py
pippy_ls/generate.py
pippy_ls/utils.py
pippy_ls/viewer.py
pippy_ls-1.1.3.dist-info/entry_points.txt
pippy_ls-1.1.3.dist-info/LICENSE
pippy_ls-1.1.3.dist-info/WHEEL
pippy_ls-1.1.3.dist-info/METADATA
pippy_ls-1.1.3.dist-info/RECORD
