Metadata-Version: 2.1
Name: pippy-ls
Version: 1.1.3
Summary: An open-source python package
Home-page: https://github.com/pradoz/pippy-ls
License: MIT
Keywords: python,package
Author: Pippy Long Stockings
Author-email: zpprado@email.com
Requires-Python: >=3.7,<4.0
Classifier: License :: OSI Approved :: MIT License
Classifier: Programming Language :: Python :: 3
Classifier: Programming Language :: Python :: 3.10
Classifier: Programming Language :: Python :: 3.7
Classifier: Programming Language :: Python :: 3.8
Classifier: Programming Language :: Python :: 3.9
Requires-Dist: aws-cdk-lib (>=2.28.0)
Requires-Dist: constructs (>=10.0.0,<11.0.0)
